Metadata-Version: 2.1
Name: pytypos
Version: 1.4.0
Summary: Typo and spelling checker
Home-page: https://github.com/PApostol/pytypos
Author: PApostol
Author-email: foo@bar.com
Maintainer: PApostol
License: MIT
Keywords: typo,spell,check
Platform: any
Classifier: Development Status :: 4 - Beta
Classifier: Intended Audience :: Developers
Classifier: License :: OSI Approved :: MIT License
Classifier: Topic :: Software Development :: Libraries
Classifier: Topic :: Utilities
Classifier: Programming Language :: Python :: 3.7
Classifier: Programming Language :: Python :: 3.8
Classifier: Programming Language :: Python :: 3.9
Classifier: Programming Language :: Python :: 3.10
Classifier: Programming Language :: Python :: 3.11
Classifier: Programming Language :: Python :: Implementation :: CPython
Classifier: Operating System :: OS Independent
Requires-Python: ~=3.7
License-File: LICENSE
